{
    "data" :  {
    "title": "1981 世代のエンジニア（もしくはそうじゃない人も）で集まってなんかしよう",
    "date": "2007-11-28 17:22:00 +0900 JST",
    "dir": "posts/2007/",
    "slug": "1128082216",
    "categories": ["tech"],
    "tags": []
}

---



<p>
  ヴァ○ナで超有名なworemacxさんと同い年生まれのことが昨日発覚。
  あともっと若いのかなと思っていたJavaScriptで超有名なamachangさんが1982年1月生まれ、つまり同年代なことが発覚。ktkr
  1981sだーーー。
</p>
<p>
  1981年代周辺のエンジニア、もしくはそうじゃない人も巻き込んで面白いことができるんじゃないか！
  前々からそう思ってたけど、現実味を帯びてきた！
</p>
<p>
  81s世代（周辺）のエンジニア＆そうじゃない人集まろうぜ！
  ということで、とりあえずIRCチャンネル作ったら、amachangが来てくれた！
  そして、ものすごい影響力のあるブログに書いてくれたよ
  →<a href="http://d.hatena.ne.jp/amachang/20071128/1196241194">1981 世代のエンジニアで集まってなんかしよう - IT戦記</a>
</p>
<p>
  まだ、IRCしかないけど、<br>
  #1981@freenode / utf-8だよ！
</p>
<p>
  なんか楽しくて面白いことしようぜ！
</p>
<h4>追記</h4>
<p>
  はてなグループも作ったよー。掲示板で自己紹介とかしてます→<a href="http://born1981.g.hatena.ne.jp/">born1981グループ</a>
</p>


 
}
