{
    "data" :  {
    "title": "椅子でぼけましょうその3",
    "date": "2006-07-28 04:56:00 +0900 JST",
    "dir": "posts/2006/",
    "slug": "0727195644",
    "categories": ["tech"],
    "tags": []
}

---



<p>
  俺的に会心のテンション。
</p>
<object height="390" width="470"><param name="movie" value="http://video.ask.jp/cmn_flash/player.swf?video_id=b8c46ba7-4c4f-4914-b215-80d11b85da42&amp;l=19&amp;logoFlg=Y">
<embed height="390" src="http://video.ask.jp/cmn_flash/player.swf?video_id=b8c46ba7-4c4f-4914-b215-80d11b85da42&amp;l=19&amp;logoFlg=Y" type="application/x-shockwave-flash" width="470"></embed></object>


 
}
