{
    "data" :  {
    "title": "生活に溶けこむコンテンツデザイン展 - 開催のお知らせ",
    "date": "2009-09-14 15:03:00 +0900 JST",
    "dir": "posts/2009/",
    "slug": "0914060315",
    "categories": ["tech"],
    "tags": []
}

---



<p>
俺は学生の時に研究室のチームで、<a href="http://www.moo-pong.com/">moo-pong</a>
という「映像（動画）を万華鏡みたいに見れるおもちゃみたいなもの」を作っていました。
そのときに支援を受けていた CREST というプロジェクトの発表会を兼ねた展示会が明日から開催されます。
俺も借り出されて、今からその準備をしにいって当日展示説明をする予定です。
moo-pong 以外にも面白いコンテンツがたくさんあるので、平日昼間から夜までですが、お時間あって興味のある方は是非いらしてください。
以下に概要を貼付けておきます。
</p>

<p>
===============================<br>
ユビキタスコンテンツショーケース2009<br>
- 生活に溶けこむコンテンツデザイン展 -<br>
2009.9.15-9.17@JASMAC八雲（東京）<br>
===============================<br>
</p>
<p>
<img alt="crest" class="at-xid-6a0133f4781589970b015435b6f55b970c" src="https://yusukebe.com/archives/a/6a0133f4781589970b015435b6f55b970c-pi.png">
</p>
<p>
JST / CREST 慶應義塾大学「ユビキタスコンテンツ製作支援
システムの研究」プロジェクトでは「ユビキタスコンテンツ
ショーケース2009 - 生活に溶けこむコンテンツデザイン展 -」
を開催いたします。
</p>
<p>
本ショーケースでは、ご来場者の皆様に実際の住宅環境の中で、
様々な衣食住遊に関係するコンテンツを体験していただきます。
また、皆様がコンテンツに触れた経験を蓄積し、経験が連動す
るコンテンツ、あるいは、経験の蓄積によって生まれる新たな
コンテンツを体験していただけます。
</p>
<p>
さらに会期中、メソドロジー、デザインをテーマとするトーク
セッション（予約制）を開催いたします。各セッションにスペ
シャルゲストを外部より招き、講演および討論を行う予定です。
皆さまのご来場をお待ちしております。
</p>
<blockquote>
日時：2009年9月15日(火)〜17日(木)　12:00-19:00<br>
場所：JASMAC 八雲<br>
　　　〒152-0023 東京都目黒区八雲5-1-3<br>
<a href="http://www.jasmac-agc.co.jp/yakumo/">http://www.jasmac-agc.co.jp/yakumo/</a><br>
　　　最寄駅：東急東横線・都立大学駅／東急田園都市線・駒沢大学駅<br>
　　　＃開催期間中は都立大学駅よりシャトルバス(無料)が運行致します。<br>
トークセッションスケジュール：<br>
　　　日　時　9月15日(火) 15:00-17:00<br>
　　　テーマ　「メソドロジー」デザインシンキングと脳科学<br>
　　　出　演　小川克彦氏（慶大教授）×奥出直人（慶大教授）<br>
　　　----------<br>
　　　日　時　9月16日(水) 15:00-17:00<br>
　　　テーマ　「デザイン」集合知、ライフログ<br>
　　　出　演　猪子寿之氏（チームラボ(株)代表取締役社長）×田中浩也（慶大準教授）<br>
　　　＃事前予約にご協力ください。満席の場合、予約いただいた方を優先<br>
　　　＃させていただきます。ご予約は下記公式サイトよりお願いします。<br>
<br>
ユビキタスコンテンツショーケース2009公式サイト：<br>
<a href="http://xtel.sfc.keio.ac.jp/jp/2009/07/2009.html">http://xtel.sfc.keio.ac.jp/jp/2009/07/2009.html</a>
</blockquote>


 
}
