{
    "data" :  {
    "title": "エロサイトの管理人説",
    "date": "2007-09-04 11:48:00 +0900 JST",
    "dir": "posts/2007/",
    "slug": "0904024840",
    "categories": ["tech"],
    "tags": []
}

---



<p>
  昔の知り合いとかに会うと、ま、みんなそうだと思うけど開口一番聞かれるのが
</p>
<blockquote>
「ゆっけ(俺のあだ名)は(仕事)なにやってるの？」
</blockquote>
<p>
っていう質問。会社勤めしてれば、「どこどこに勤めて、なになにをやってますよ」
なんて簡単に答えられるんだけどさ。
俺、今は自宅で親父と共にフリーランスみたいな仕事やってる上、
そのやってる内容を説明するのが結構めんどいわけ。
だから、最近冗談のつもりで、
</p>
<blockquote>
「エロサイトの管理人やってます」
</blockquote>
<p>
ってみんなに答えてる。
でさ、その場で友達と話す分には笑って済まされるんだけど、
よくよく考えてみたら、その後、
俺がタッチしてない場所で
</p>
<blockquote>
「ゆっけ、エロサイトの管理人やってるらしいよ」
</blockquote>
<p>
なんていううわさが飛び交う可能性あるよね。
俺＝エロサイトの管理人っていう式が完全に成り立つ。
なんかこれがネタじゃなくて、本気にされちゃうとなんだか「恥」だなと思ったから、
ちょっと記事として書いてみたよ。
</p>
<p>
だから言う。
</p>
<blockquote>
「俺はエロサイトの管理人じゃないよ！<br>
　いや、『<strong>語弊</strong>』があった、エロサイトの管理だけしているわけじゃないからね！<br>
　ちゃんとした仕事もしてるよ！」<br>
</blockquote>
<p>
『語弊』があったというのは実際のところ、「エロサイトの管理人」というのもあながち嘘ではないから(ｗ)。
  以前作った<a href="http://pulpsite.net/eropla/">ERO Pla</a>とか<a href="http://pulpsite.net/erolyst/">エロリスト</a>とかのアフィリエイトの収入が右肩上がりに上昇していて、
先月の収入とかやばかった(公表はしません、ものすごいリクエストがあれば教えるかも。
あ、念のため言っておくと、ちゃんとこれ会社の売り上げとして計上してますよ。
税金払ってますよ)。
しかもさらに、俺の頭の中からは新しいエロサイトのアイデアがどんどん浮かぶんだけど。
だてに「ゆー<strong>すけべ</strong>ー日記」名乗ってるわけじゃないね。
そのうちほんとに、こりゃ完全なるエロサイトの管理人になるかもしれんな。
ということで、俺はエロサイトの管理人してるだけじゃないからね！
まともな仕事も(たまにはｗ)してるよ！
</p>


 
}
